ollama_code_cli/.DS_Store
ollama_code_cli/__init__.py
ollama_code_cli/cli/.DS_Store
ollama_code_cli/cli/__init__.py
ollama_code_cli/cli/cli.py
ollama_code_cli/tools/.DS_Store
ollama_code_cli/tools/__init__.py
ollama_code_cli/tools/tool_manager.py
ollama_code_cli-1.0.3.dist-info/WHEEL
ollama_code_cli-1.0.3.dist-info/entry_points.txt
ollama_code_cli-1.0.3.dist-info/METADATA
ollama_code_cli-1.0.3.dist-info/RECORD
