Metadata-Version: 2.4
Name: ollama-code-cli
Version: 1.0.3
Summary: A CLI tool for agentic coding tasks using local LLMs with tool calling
Keywords: cli,ollama,llm,ai,coding
Author: Vigyat Goel
Author-email: Vigyat Goel <vigyatgoel@gmail.com>
License-Expression: MIT
Classifier: Development Status :: 4 - Beta
Classifier: Intended Audience :: Developers
Classifier: Programming Language :: Python :: 3
Classifier: Programming Language :: Python :: 3.10
Classifier: Programming Language :: Python :: 3.11
Classifier: Programming Language :: Python :: 3.12
Classifier: Programming Language :: Python :: 3.13
Requires-Dist: click>=8.2.1
Requires-Dist: ollama>=0.5.3
Requires-Dist: prompt-toolkit>=3.0.52
Requires-Dist: rich>=13.7.1
Requires-Dist: yaspin>=3.1.0
Requires-Python: >=3.10
Project-URL: Homepage, https://github.com/vigyatgoel/ollama-code-cli
Project-URL: Issues, https://github.com/vigyatgoel/ollama-code-cli/issues
Project-URL: Repository, https://github.com/vigyatgoel/ollama-code-cli
